setup.py
sqlpool/SqlPool.py
sqlpool.egg-info/PKG-INFO
sqlpool.egg-info/SOURCES.txt
sqlpool.egg-info/dependency_links.txt
sqlpool.egg-info/top_level.txt