Metadata-Version: 1.0
Name: sqlpool
Version: 0.0.2
Summary: mysql,sqlserver,oracle poll
Home-page: https://github.com/szmgithubcode/
Author: zhaozhi
Author-email: 13546120129@sina.cn
License: UNKNOWN
Platform: UNKNOWN
